versionoverlord/Common.py
versionoverlord/DisplayVersions.py
versionoverlord/EnvironmentBase.py
versionoverlord/FileNameToSlugs.py
versionoverlord/IHandler.py
versionoverlord/SlugHandler.py
versionoverlord/TemplateHandler.py
versionoverlord/__init__.py
versionoverlord/_version.py
versionoverlord/circleci/HandleCircleCI.py
versionoverlord/circleci/__init__.py
versionoverlord/commands/BumpVersion.py
versionoverlord/commands/CreateSpecification.py
versionoverlord/commands/DraftRelease.py
versionoverlord/commands/PickDependencies.py
versionoverlord/commands/PublishRelease.py
versionoverlord/commands/QuerySlugs.py
versionoverlord/commands/TagType.py
versionoverlord/commands/UpdateDependencies.py
versionoverlord/commands/VersionOverlord.py
versionoverlord/commands/__init__.py
versionoverlord/exceptions/ProjectNotSetException.py
versionoverlord/exceptions/ProjectsBaseNotSetException.py
versionoverlord/exceptions/__init__.py
versionoverlord/githubadapter/GitHubAdapter.py
versionoverlord/githubadapter/GitHubAdapterError.py
versionoverlord/githubadapter/GitHubAdapterTypes.py
versionoverlord/githubadapter/__init__.py
versionoverlord/pyprojecttoml/HandlePyProjectToml.py
versionoverlord/pyprojecttoml/__init__.py
versionoverlord/requirements/HandleRequirementsTxt.py
versionoverlord/requirements/__init__.py
versionoverlord/resources/__init__.py
versionoverlord/resources/loggingConfiguration.json
versionoverlord/setup/HandleSetupPy.py
versionoverlord/setup/__init__.py
versionoverlord/travisci/HandleTravisCI.py
versionoverlord/travisci/__init__.py
versionoverlord-2.5.0.dist-info/licenses/LICENSE
versionoverlord-2.5.0.dist-info/METADATA
versionoverlord-2.5.0.dist-info/WHEEL
versionoverlord-2.5.0.dist-info/entry_points.txt
versionoverlord-2.5.0.dist-info/top_level.txt
versionoverlord-2.5.0.dist-info/RECORD
